bionemo/moco/__init__.py
bionemo/moco/distributions/__init__.py
bionemo/moco/distributions/prior/__init__.py
bionemo/moco/distributions/prior/distribution.py
bionemo/moco/distributions/prior/continuous/__init__.py
bionemo/moco/distributions/prior/continuous/gaussian.py
bionemo/moco/distributions/prior/continuous/harmonic.py
bionemo/moco/distributions/prior/continuous/utils.py
bionemo/moco/distributions/prior/discrete/__init__.py
bionemo/moco/distributions/prior/discrete/custom.py
bionemo/moco/distributions/prior/discrete/mask.py
bionemo/moco/distributions/prior/discrete/uniform.py
bionemo/moco/distributions/time/__init__.py
bionemo/moco/distributions/time/beta.py
bionemo/moco/distributions/time/distribution.py
bionemo/moco/distributions/time/logit_normal.py
bionemo/moco/distributions/time/uniform.py
bionemo/moco/distributions/time/utils.py
bionemo/moco/interpolants/__init__.py
bionemo/moco/interpolants/base_interpolant.py
bionemo/moco/interpolants/batch_augmentation.py
bionemo/moco/interpolants/continuous_time/__init__.py
bionemo/moco/interpolants/continuous_time/continuous/__init__.py
bionemo/moco/interpolants/continuous_time/continuous/continuous_flow_matching.py
bionemo/moco/interpolants/continuous_time/continuous/vdm.py
bionemo/moco/interpolants/continuous_time/continuous/data_augmentation/__init__.py
bionemo/moco/interpolants/continuous_time/continuous/data_augmentation/augmentation_types.py
bionemo/moco/interpolants/continuous_time/continuous/data_augmentation/equivariant_ot_sampler.py
bionemo/moco/interpolants/continuous_time/continuous/data_augmentation/kabsch_augmentation.py
bionemo/moco/interpolants/continuous_time/continuous/data_augmentation/ot_sampler.py
bionemo/moco/interpolants/continuous_time/discrete/__init__.py
bionemo/moco/interpolants/continuous_time/discrete/discrete_flow_matching.py
bionemo/moco/interpolants/continuous_time/discrete/mdlm.py
bionemo/moco/interpolants/discrete_time/__init__.py
bionemo/moco/interpolants/discrete_time/utils.py
bionemo_moco-0.0.2.2.dist-info/licenses/LICENSE
bionemo_moco-0.0.2.2.dist-info/METADATA
bionemo_moco-0.0.2.2.dist-info/WHEEL
bionemo_moco-0.0.2.2.dist-info/top_level.txt
bionemo_moco-0.0.2.2.dist-info/RECORD
