Metadata-Version: 2.4
Name: bionemo-moco
Version: 0.0.2.2
Summary: BioNeMo Modular Co-Design: Making building Diffusion and Flow Matching generative models easier
Author-email: BioNeMo Team <bionemofeedback@nvidia.com>
License: 
Requires-Python: >=3.10
License-File: LICENSE
Requires-Dist: torch>=2.2
Requires-Dist: numpy<2,>=1.24.4
Requires-Dist: jaxtyping>=0.2.34
Requires-Dist: pot>=0.9.5
Requires-Dist: scikit-learn>=1.6.0
Requires-Dist: matplotlib>=3.3.2
Dynamic: license-file
